{"case_id":"AML-2026-001","customer_profile":{"name":"Mia Torres","segment":"retail","country":"US","occupation_or_industry":"hospitality","risk_rating":"medium"},"alerts":[{"alert_type":"structuring","score":88,"description":"Multiple deposits below threshold","triggered_rules":["R-CTR-01"]}],"transactions":[{"date":"2026-07-01","amount":9800,"currency":"USD","type":"cash_deposit","channel":"branch","direction":"inbound","destination_country":"US"},{"date":"2026-07-03","amount":9700,"currency":"USD","type":"cash_deposit","channel":"branch","direction":"inbound","destination_country":"US"},{"date":"2026-07-05","amount":9600,"currency":"USD","type":"cash_deposit","channel":"branch","direction":"inbound","destination_country":"US"},{"date":"2026-07-06","amount":9500,"currency":"USD","type":"transfer","channel":"online","direction":"outbound","destination_country":"MX"},{"date":"2026-07-07","amount":9400,"currency":"USD","type":"transfer","channel":"online","direction":"outbound","destination_country":"MX"}],"analyst_notes":"Pattern appears clustered around weekly business close.","supporting_context":"Account opened 8 months ago"}
